<?xml version="1.0" encoding="utf-8"?>
<!DOCTYPE Bibliothek SYSTEM "bibliothek.dtd">
<Bibliothek>
	<Abteilung>
		<Buch id="1">
			<ISBN>978-3-7742-1142-1</ISBN>
			<Titel>Basic cooking</Titel>
			<Autor>Sabine Saelzer</Autor>
			<Co-Autor>Sebastian Dickhaut</Co-Autor>
			<Co-Autor>Barbara Bonisolli</Co-Autor>
			<Co-Autor>Alexander Walter</Co-Autor>
			<Auflage>27</Auflage>
			<Jahr>2013</Jahr>
		</Buch>
		<Buch id="2">
			<ISBN>978-1-4454-5973-8</ISBN>
			<Titel>Studentenkueche</Titel>
			<Verlag>Parragon</Verlag>
			<Jahr>2012</Jahr>
		</Buch>
		<Buch id="3">
			<ISBN>978-1-4748-2866-6</ISBN>
			<Titel>Mediterran</Titel>
			<Verlag>Parragon</Verlag>
		</Buch>
	</Abteilung>
</Bibliothek>
